packaging_version_increment/__init__.py
packaging_version_increment/enums.py
packaging_version_increment/increment.py
packaging_version_increment/version.py
packaging_version_increment-0.1.3.dist-info/LICENSE
packaging_version_increment-0.1.3.dist-info/METADATA
packaging_version_increment-0.1.3.dist-info/WHEEL
packaging_version_increment-0.1.3.dist-info/top_level.txt
packaging_version_increment-0.1.3.dist-info/RECORD
